raanova/__init__.py
raanova/linear_regression/__init__.py
raanova/linear_regression/helper_functions.py
raanova/linear_regression/lasso.py
raanova/linear_regression/linear_regression.py
raanova/linear_regression/ols.py
raanova/linear_regression/ridge.py
raanova/linear_regression/wls.py
raanova/visualisation/__init__.py
raanova/visualisation/visualisation.py
raanova-1.0.0.dist-info/LICENSE
raanova-1.0.0.dist-info/METADATA
raanova-1.0.0.dist-info/WHEEL
raanova-1.0.0.dist-info/top_level.txt
raanova-1.0.0.dist-info/RECORD
