Metadata-Version: 2.1
Name: raanova
Version: 1.0.0
Author: Mila Pourali, Andrew Rambidis
Author-email: Aurélien Bück-Kaeffer <aurelien.buck.kaeffer@gmail.com>
License: MIT License
Project-URL: Repository, https://github.com/Scezaquer/MATH-533-F2023
Classifier: Programming Language :: Python :: 3
Requires-Python: >=3.12.0
License-File: LICENSE
Requires-Dist: numpy >=1.26.0
Requires-Dist: scipy >=1.11.0
Requires-Dist: matplotlib >=3.8.0
Provides-Extra: dev
